odoo/addons/account_product_fiscal_classification_test/README.rst
odoo/addons/account_product_fiscal_classification_test/__init__.py
odoo/addons/account_product_fiscal_classification_test/__manifest__.py
odoo/addons/account_product_fiscal_classification_test/demo/account_product_fiscal_classification_template.xml
odoo/addons/account_product_fiscal_classification_test/demo/account_tax_template.xml
odoo/addons/account_product_fiscal_classification_test/i18n/account_product_fiscal_classification_test.pot
odoo/addons/account_product_fiscal_classification_test/i18n/fr.po
odoo/addons/account_product_fiscal_classification_test/i18n/pt.po
odoo/addons/account_product_fiscal_classification_test/readme/CONTRIBUTORS.rst
odoo/addons/account_product_fiscal_classification_test/readme/DESCRIPTION.rst
odoo/addons/account_product_fiscal_classification_test/static/description/icon.png
odoo/addons/account_product_fiscal_classification_test/static/description/index.html
odoo/addons/account_product_fiscal_classification_test/tests/__init__.py
odoo/addons/account_product_fiscal_classification_test/tests/test_module.py
odoo/addons/account_product_fiscal_classification_test/tests/test_multicompany.py
odoo12_addon_account_product_fiscal_classification_test-12.0.1.1.0.dist-info/METADATA
odoo12_addon_account_product_fiscal_classification_test-12.0.1.1.0.dist-info/WHEEL
odoo12_addon_account_product_fiscal_classification_test-12.0.1.1.0.dist-info/top_level.txt
odoo12_addon_account_product_fiscal_classification_test-12.0.1.1.0.dist-info/RECORD
