Metadata-Version: 2.1
Name: odoo12-addon-account-product-fiscal-classification-test
Version: 12.0.1.1.0
Summary: tests account_product_fiscal_classification module
Home-page: https://github.com/OCA/account-fiscal-rule
Author: Akretion,GRAP,La Louve,Odoo Community Association (OCA)
Author-email: support@odoo-community.org
License: AGPL-3
Platform: UNKNOWN
Classifier: Programming Language :: Python
Classifier: Framework :: Odoo
Classifier: License :: OSI Approved :: GNU Affero General Public License v3
Requires-Python: >=3.5
Requires-Dist: odoo12-addon-account-product-fiscal-classification
Requires-Dist: odoo (<12.1dev,>=12.0a)
